etc/servicewall/realms.json
etc/servicewall/ulogd.conf
etc/servicewall/services/.keepme
etc/systemd/system/servicewall-logs.service
etc/systemd/system/servicewall-logs.socket
etc/systemd/system/servicewall-ulogd.service
etc/systemd/system/servicewall.service
etc/xdg/autostart/servicewall-systray.desktop
servicewall/__init__.py
servicewall/_version.py
servicewall/firewall.py
servicewall/main.py
servicewall/network_helpers.py
servicewall/parser_helpers.py
servicewall/service_helpers.py
servicewall/statefulfirewall.py
servicewall-0.4.9.data/data/lib/servicewall/icon.png
servicewall-0.4.9.data/data/lib/servicewall/icon2.png
servicewall-0.4.9.data/data/lib/servicewall/services.p
servicewall-0.4.9.data/data/lib/servicewall/systray.py
servicewall-0.4.9.data/data/lib/servicewall/toggler
servicewall-0.4.9.data/scripts/sw
servicewall-0.4.9.dist-info/LICENSE
servicewall-0.4.9.dist-info/METADATA
servicewall-0.4.9.dist-info/WHEEL
servicewall-0.4.9.dist-info/top_level.txt
servicewall-0.4.9.dist-info/RECORD
