Metadata-Version: 2.1
Name: servicewall
Version: 0.4.9
Summary: The firewall that remembers the different network you connect to.
Home-page: https://git.relatif.moi/lafleur/servicewall
Author: la Fleur
Author-email: lafleur@boum.org
License: GNUv3
Keywords: dynamic adaptable iptables firewall
Platform: UNKNOWN
Classifier: Development Status :: 4 - Beta
Classifier: Programming Language :: Python :: 3
Classifier: License :: OSI Approved :: GNU General Public License v3 (GPLv3)
Classifier: Operating System :: POSIX
Requires-Python: >=3
Requires-Dist: argparse
Requires-Dist: arpreq
Requires-Dist: python-iptables
Requires-Dist: python-systemd
Provides-Extra: argument_completion_as_root
Requires-Dist: argcomplete ; extra == 'argument_completion_as_root'
